pyramid_elasticapm/__init__.py
pyramid_elasticapm/tests/__init__.py
pyramid_elasticapm/tests/conftest.py
pyramid_elasticapm/tests/test_plugin.py
pyramid_elasticapm-1.2.0.dist-info/LICENSE
pyramid_elasticapm-1.2.0.dist-info/METADATA
pyramid_elasticapm-1.2.0.dist-info/WHEEL
pyramid_elasticapm-1.2.0.dist-info/top_level.txt
pyramid_elasticapm-1.2.0.dist-info/RECORD
