Metadata-Version: 2.1
Name: pyramid-elasticapm
Version: 1.2.0
Summary: elastic-apm integration for the Pyramid framework
Home-page: https://github.com/risclog-solution/pyramid-elasticapm
Author: Sebastian Wehrmann (riscLOG Solution GmbH)
Author-email: sebastian@risclog.com
License: BSD
Keywords: elastic apm pyramid
Classifier: License :: OSI Approved :: BSD License
Classifier: Programming Language :: Python
Classifier: Programming Language :: Python :: 3
Classifier: Programming Language :: Python :: 3.9
Classifier: Programming Language :: Python :: 3.10
Classifier: Programming Language :: Python :: 3.11
Classifier: Programming Language :: Python :: 3 :: Only
License-File: LICENSE
Requires-Dist: elastic-apm
Requires-Dist: pyramid
Provides-Extra: test
Requires-Dist: pytest ; extra == 'test'
Requires-Dist: pytest-cache ; extra == 'test'
Requires-Dist: pytest-cov ; extra == 'test'
Requires-Dist: pytest-rerunfailures ; extra == 'test'
Requires-Dist: pytest-sugar ; extra == 'test'
Requires-Dist: webtest ; extra == 'test'
Requires-Dist: pytest-localserver ; extra == 'test'
Requires-Dist: elastic-apm <6.8 ; extra == 'test'
